jax_plugins/xla_rocm60/__init__.py
jax_plugins/xla_rocm60/version.py
jax_plugins/xla_rocm60/xla_rocm_plugin.so
jax_rocm60_pjrt-0.5.0.dist-info/METADATA
jax_rocm60_pjrt-0.5.0.dist-info/WHEEL
jax_rocm60_pjrt-0.5.0.dist-info/entry_points.txt
jax_rocm60_pjrt-0.5.0.dist-info/top_level.txt
jax_rocm60_pjrt-0.5.0.dist-info/RECORD
