Metadata-Version: 2.1
Name: jax-rocm60-pjrt
Version: 0.5.0
Summary: JAX XLA PJRT Plugin for AMD GPUs (ROCm:unknown)
Home-page: https://github.com/jax-ml/jax
Author: Ruturaj4
Author-email: Ruturaj.Vaidya@amd.com
License: Apache-2.0
Classifier: Development Status :: 3 - Alpha
Classifier: Programming Language :: Python :: 3
